setup.py
cloudsns/__init__.py
cloudsns/cloudlistener.py
cloudsns/message.py
cloudsns.egg-info/PKG-INFO
cloudsns.egg-info/SOURCES.txt
cloudsns.egg-info/dependency_links.txt
cloudsns.egg-info/requires.txt
cloudsns.egg-info/top_level.txt
cloudsns/integration_test/__init__.py
cloudsns/integration_test/create.py