Metadata-Version: 1.0
Name: cloudsns
Version: 0.0.1
Summary: Listener for cloudformation events
Home-page: https://github.com/remind101/cloudsns
Author: Tom Taubkin
Author-email: tomtaubkin@gmail.com
License: New BSD license
Platform: UNKNOWN
